simple_storage_service/__init__.py
simple_storage_service/exceptions.py
simple_storage_service/factory.py
simple_storage_service/providers/__init__.py
simple_storage_service/providers/aws.py
simple_storage_service/providers/azure.py
simple_storage_service/providers/base_provider.py
simple_storage_service/providers/gcp.py
tests/__init__.py
tests/test_exceptions.py
tests/test_provider_validation_config.py
tests/test_simple_usage.py
tests/test_storage_factory.py
simple_storage_service-0.0.5.dist-info/LICENSE
simple_storage_service-0.0.5.dist-info/METADATA
simple_storage_service-0.0.5.dist-info/WHEEL
simple_storage_service-0.0.5.dist-info/top_level.txt
simple_storage_service-0.0.5.dist-info/RECORD
