Metadata-Version: 2.1
Name: simple-storage-service
Version: 0.0.5
Summary: Assist in the handling of files on storages from different providers.
Home-page: https://gitlab.com/r13/educat-community/simple-storage-service
Author: Lucas Nascimento Huati Corrêa
Author-email: lucas@educat.net.br
Classifier: Programming Language :: Python :: 3
Classifier: License :: OSI Approved :: MIT License
Classifier: Operating System :: OS Independent
Requires-Python: >=3.6
License-File: LICENSE
Requires-Dist: boto3 (==1.20.10)
Requires-Dist: azure-storage-blob (==2.0.1)
Requires-Dist: google-cloud-storage (==1.36.0)
